{"status":"success","data":{"content":{"content_id":"22","title":"\u66a7\u6627\uff1a\u7ed9\u65e5\u672c\u8111\u6d1e\u4e00\u4e2a\u54f2\u5b66\u89e3\u91ca","small_background_img":"http:\/\/cdn.vistopia.com.cn\/1541157329701.png","background_img":"http:\/\/cdn.vistopia.com.cn\/1541476786125.jpg","catalog_type":"1","type":"charge","complete_class_price":"28.00","promotion_price":"28.00","promotion_desc":"\u9650\u65f6\u7279\u60e0","is_promotion":"0","media_type":"1","is_vip_free":"1","is_vip_only":"0","avatar":"http:\/\/cdn.vistopia.com.cn\/1541157601994.jpg","text_desc":"\u590d\u65e6\u5927\u5b66\u54f2\u5b66\u5b66\u9662\u6559\u6388","media_type_en":"audio","author":"\u5f90\u82f1\u747e","is_purchased":"0","is_subscribed":"0","vip_type":"lixiangjia_trial","is_vip_expired":"0","old_vip_type":"","is_limited_free":"0"},"catalogs":[{"catalog_id":"35","catalog_title":"\u63a8\u8350\u8bed"},{"catalog_id":"36","catalog_title":"\u53d1\u520a\u8bcd"},{"catalog_id":"37","catalog_title":"\u8d85\u8d8a\u300a\u83ca\u4e0e\u5200\u300b"},{"catalog_id":"38","catalog_title":"\u65e5\u8bed\u4e0e\u66a7\u6627"},{"catalog_id":"40","catalog_title":"\u573a\u6240\u903b\u8f91\u4e0e\u66a7\u6627"},{"catalog_id":"41","catalog_title":"\u5076\u7136\u6027\u54f2\u5b66\u4e0e\u66a7\u6627"},{"catalog_id":"46","catalog_title":"\u5206\u6790\u54f2\u5b66\u4e0e\u66a7\u6627"},{"catalog_id":"48","catalog_title":"\u98ce\u571f\u6982\u5ff5\u4e0e\u66a7\u6627"},{"catalog_id":"49","catalog_title":"\u5171\u8363\u5708\u4e0e\u66a7\u6627"},{"catalog_id":"68","catalog_title":"\u756a\u5916"}],"articles":[{"article_id":"50804","content_id":"22","catalog_id":"35","title":"\u6881\u6587\u9053\uff1a\u65e5\u672c\u662f\u4e00\u4e2a\u6211\u4eec\u7ed5\u4e0d\u5f00\u7684\u8bdd\u9898","sort_number":"00","status":"1","share_desc":"\u65e5\u672c\u662f\u4e00\u4e2a\u6211\u4eec\u7ed5\u4e0d\u5f00\u7684\u8bfe\u9898\u3002","is_trial":"1","duration":"105","duration_str":"1:44","media_type":"1","media_size":"1653","video_poster":null,"comment_count":"20","sample_media_key":"aud\/116090\/7b6c0d1f8cc81af473aa9e383f95c49c.mp3","vid":"v0d265g10002cccskjhabc6lp42phul0","sample_vid":"v0d265g10002ccct3jpabc6lp42pi9v0","card_data":"","media_key_full_url":"http:\/\/cdn5.vistopia.com.cn\/1541160903172.mp3","optional_media_key_full_url":"http:\/\/cdn.vistopia.com.cn\/1541160903172.mp3","share_url":"https:\/\/shop.vistopia.com.cn\/article?article_id=50804","media_type_en":"audio","content_media_type_en":"audio","type":"charge","content_url":"https:\/\/api.vistopia.com.cn\/api\/v1\/web\/article-content\/ZX9gg","sample_media_full_url":"http:\/\/cdn.vistopia.com.cn\/aud\/116090\/7b6c0d1f8cc81af473aa9e383f95c49c.mp3","card_desc":"\u65e5\u672c\u662f\u4e00\u4e2a\u6211\u4eec\u7ed5\u4e0d\u5f00\u7684\u8bfe\u9898\u3002","is_listened":"0","listen_percent":"0","listen_time":"0","is_finished":"0","is_vip_free":"1","background_img":"http:\/\/cdn.vistopia.com.cn\/1541476786125.jpg","author":"\u5f90\u82f1\u747e","is_vip_only":"0","share_free_count":"0","is_listen":"1"},{"article_id":"50854","content_id":"22","catalog_id":"36","title":"0. \u4e3a\u4ec0\u4e48\u8981\u4ece\u54f2\u5b66\u89d2\u5ea6\u770b\u65e5\u672c\u6587\u5316\uff1f","sort_number":"01","status":"1","share_desc":"\u5bf9\u4ed8\u8111\u56de\u8def\u5343\u8f6c\u767e\u56de\u7684\u65e5\u672c\u4eba\uff0c\u4e5f\u53ea\u6709\u8111\u6d1e\u6e05\u6670\u7684\u54f2\u5b66\u53ef\u4ee5\u80dc\u4efb\u4e86\u3002","is_trial":"1","duration":"815","duration_str":"13:35","media_type":"1","media_size":"12765","video_poster":"http:\/\/cdn.vistopia.com.cn\/upload_img.png","comment_count":"53","sample_media_key":"aud\/133901\/7ea8271fa423edb2c5b5b6df2a6c0a10.mp3","vid":"v0d265g10002cccskjv8v1n1s3nrcv80","sample_vid":"v0d265g10002ccct3kpabc6lp42pia4g","card_data":"","media_key_full_url":"http:\/\/cdn5.vistopia.com.cn\/1541339010860.mp3","optional_media_key_full_url":"http:\/\/cdn.vistopia.com.cn\/1541339010860.mp3","share_url":"https:\/\/shop.vistopia.com.cn\/article?article_id=50854","media_type_en":"audio","content_media_type_en":"audio","type":"charge","content_url":"https:\/\/api.vistopia.com.cn\/api\/v1\/web\/article-content\/SklUP","sample_media_full_url":"http:\/\/cdn.vistopia.com.cn\/aud\/133901\/7ea8271fa423edb2c5b5b6df2a6c0a10.mp3","card_desc":"\u5bf9\u4ed8\u8111\u56de\u8def\u5343\u8f6c\u767e\u56de\u7684\u65e5\u672c\u4eba\uff0c\u4e5f\u53ea\u6709\u8111\u6d1e\u6e05\u6670\u7684\u54f2\u5b66\u53ef\u4ee5\u80dc\u4efb\u4e86\u3002","is_listened":"0","listen_percent":"0","listen_time":"0","is_finished":"0","is_vip_free":"1","background_img":"http:\/\/cdn.vistopia.com.cn\/1541476786125.jpg","author":"\u5f90\u82f1\u747e","is_vip_only":"0","share_free_count":"0","is_listen":"1"},{"article_id":"50904","content_id":"22","catalog_id":"37","title":"1. \u8c08\u8c08\u5bf9\u65e5\u672c\u6587\u5316\u7684\u8bef\u8bfb","sort_number":"02","status":"1","share_desc":"\u803b\u611f\u6587\u5316\u4e0d\u662f\u65e5\u672c\u6587\u5316\u7684\u6838\u5fc3\u3002","is_trial":"0","duration":"1093","duration_str":"18:13","media_type":"1","media_size":"17092","video_poster":"http:\/\/cdn.vistopia.com.cn\/upload_img.png","comment_count":"140","sample_media_key":"aud\/133907\/1a8311e4597e800efa490e4d56dae240.mp3","vid":"v03265g10002cccskjqh3be9vs2846e0","sample_vid":"v0d265g10002ccct3k9abc6lp42pia10","card_data":"","media_key_full_url":"http:\/\/cdn5.vistopia.com.cn\/1541339071259.mp3","optional_media_key_full_url":"http:\/\/cdn.vistopia.com.cn\/1541339071259.mp3","share_url":"https:\/\/shop.vistopia.com.cn\/article?article_id=50904&share_uid=jquKk","media_type_en":"audio","content_media_type_en":"audio","type":"charge","content_url":"https:\/\/api.vistopia.com.cn\/api\/v1\/web\/article-content\/F2C1W","sample_media_full_url":"http:\/\/cdn.vistopia.com.cn\/aud\/133907\/1a8311e4597e800efa490e4d56dae240.mp3","card_desc":"\u803b\u611f\u6587\u5316\u4e0d\u662f\u65e5\u672c\u6587\u5316\u7684\u6838\u5fc3\u3002","is_listened":"0","listen_percent":"0","listen_time":"0","is_finished":"0","is_vip_free":"1","background_img":"http:\/\/cdn.vistopia.com.cn\/1541476786125.jpg","author":"\u5f90\u82f1\u747e","is_vip_only":"0","share_free_count":"10","is_listen":"1"},{"article_id":"50954","content_id":"22","catalog_id":"38","title":"2. \u65e5\u672c\u4eba\u539f\u6765\u662f\u8fd9\u6837\u5949\u627f\u4eba\u7684","sort_number":"03","status":"1","share_desc":"\u65e5\u672c\u4eba\u4e3a\u4ec0\u4e48\u4e0d\u597d\u597d\u8bf4\u8bdd\uff1f","is_trial":"1","duration":"940","duration_str":"15:40","media_type":"1","media_size":"14708","video_poster":"http:\/\/cdn.vistopia.com.cn\/upload_img.png","comment_count":"93","sample_media_key":"aud\/134047\/f019029f22edcbf284b76c27442a19bd.mp3","vid":"v03265g10002cccskjioktor4971fj3g","sample_vid":"v0d265g10002ccct3khabc6lp42pia2g","card_data":"","media_key_full_url":"http:\/\/cdn5.vistopia.com.cn\/1541340473603.mp3","optional_media_key_full_url":"http:\/\/cdn.vistopia.com.cn\/1541340473603.mp3","share_url":"https:\/\/shop.vistopia.com.cn\/article?article_id=50954","media_type_en":"audio","content_media_type_en":"audio","type":"charge","content_url":"https:\/\/api.vistopia.com.cn\/api\/v1\/web\/article-content\/hAraU","sample_media_full_url":"http:\/\/cdn.vistopia.com.cn\/aud\/134047\/f019029f22edcbf284b76c27442a19bd.mp3","card_desc":"\u65e5\u672c\u4eba\u4e3a\u4ec0\u4e48\u4e0d\u597d\u597d\u8bf4\u8bdd\uff1f","is_listened":"0","listen_percent":"0","listen_time":"0","is_finished":"0","is_vip_free":"1","background_img":"http:\/\/cdn.vistopia.com.cn\/1541476786125.jpg","author":"\u5f90\u82f1\u747e","is_vip_only":"0","share_free_count":"0","is_listen":"1"},{"article_id":"51004","content_id":"22","catalog_id":"38","title":"3. \u65e5\u672c\u4eba\u4e3a\u4ec0\u4e48\u4e0d\u201c\u597d\u597d\u8bf4\u8bdd\u201d\uff1f","sort_number":"04","status":"1","share_desc":"\u65e5\u672c\u4eba\u5e38\u5e38\u89c9\u5f97\u81ea\u5df1\u662f\u4e00\u6761\u866b\u5b50\uff1f","is_trial":"1","duration":"643","duration_str":"10:43","media_type":"1","media_size":"10070","video_poster":"http:\/\/cdn.vistopia.com.cn\/upload_img.png","comment_count":"59","sample_media_key":"aud\/134132\/515d582858df18838902de7056dcc3f3.mp3","vid":"v02265g10002cccskjoijgv73ie33vq0","sample_vid":"v0d265g10002ccct3k1abc6lp42pia0g","card_data":"","media_key_full_url":"http:\/\/cdn5.vistopia.com.cn\/1541341323101.mp3","optional_media_key_full_url":"http:\/\/cdn.vistopia.com.cn\/1541341323101.mp3","share_url":"https:\/\/shop.vistopia.com.cn\/article?article_id=51004","media_type_en":"audio","content_media_type_en":"audio","type":"charge","content_url":"https:\/\/api.vistopia.com.cn\/api\/v1\/web\/article-content\/Kgzot","sample_media_full_url":"http:\/\/cdn.vistopia.com.cn\/aud\/134132\/515d582858df18838902de7056dcc3f3.mp3","card_desc":"\u65e5\u672c\u4eba\u5e38\u5e38\u89c9\u5f97\u81ea\u5df1\u662f\u4e00\u6761\u866b\u5b50\uff1f","is_listened":"0","listen_percent":"0","listen_time":"0","is_finished":"0","is_vip_free":"1","background_img":"http:\/\/cdn.vistopia.com.cn\/1541476786125.jpg","author":"\u5f90\u82f1\u747e","is_vip_only":"0","share_free_count":"0","is_listen":"1"},{"article_id":"51504","content_id":"22","catalog_id":"40","title":"4. \u66a7\u6627\u662f\u4e00\u79cd\u53cd\u5927\u6570\u636e\u7684\u6587\u5316","sort_number":"05","status":"1","share_desc":"\u66a7\u6627\u662f\u4eba\u7c7b\u601d\u60f3\u7684\u539f\u59cb\u6c64\u3002","is_trial":"0","duration":"978","duration_str":"16:18","media_type":"1","media_size":"12628","video_poster":"http:\/\/cdn.vistopia.com.cn\/upload_img.png","comment_count":"74","sample_media_key":"aud\/285693\/34ad918461928f4b2b34a95cfe789a5d.mp3","vid":"v03265g10002cccskkih3be9vs2846eg","sample_vid":"v0d265g10002ccct3lv8v1n1s3nrdbo0","card_data":"","media_key_full_url":"http:\/\/cdn5.vistopia.com.cn\/1542856933696.mp3","optional_media_key_full_url":"http:\/\/cdn.vistopia.com.cn\/1542856933696.mp3","share_url":"https:\/\/shop.vistopia.com.cn\/article?article_id=51504&share_uid=zG5v6","media_type_en":"audio","content_media_type_en":"audio","type":"charge","content_url":"https:\/\/api.vistopia.com.cn\/api\/v1\/web\/article-content\/XTgjY","sample_media_full_url":"http:\/\/cdn.vistopia.com.cn\/aud\/285693\/34ad918461928f4b2b34a95cfe789a5d.mp3","card_desc":"\u66a7\u6627\u662f\u4eba\u7c7b\u601d\u60f3\u7684\u539f\u59cb\u6c64\u3002","is_listened":"0","listen_percent":"0","listen_time":"0","is_finished":"0","is_vip_free":"1","background_img":"http:\/\/cdn.vistopia.com.cn\/1541476786125.jpg","author":"\u5f90\u82f1\u747e","is_vip_only":"0","share_free_count":"10","is_listen":"1"},{"article_id":"51554","content_id":"22","catalog_id":"41","title":"5. \u66a7\u6627\uff0c\u65e5\u672c\u4eba\u7684\u5feb\u4e50\u54f2\u5b66","sort_number":"06","status":"1","share_desc":"\u6251\u9762\u800c\u6765\u7684\u547d\u8fd0\uff0c\u662f\u66a7\u6627\u6587\u5316\u8981\u4f60\u53bb\u63a5\u53d7\u7684\u4e8b\u60c5\u3002","is_trial":"0","duration":"855","duration_str":"14:15","media_type":"1","media_size":"13454","video_poster":"http:\/\/cdn.vistopia.com.cn\/upload_img.png","comment_count":"68","sample_media_key":"aud\/173399\/043ebf37671b8b362058c732155edd9d.mp3","vid":"v02265g10002cccskkar686qbamp29lg","sample_vid":"v0d265g10002ccct3l78v1n1s3nrdbl0","card_data":"","media_key_full_url":"http:\/\/cdn5.vistopia.com.cn\/1541733991084.mp3","optional_media_key_full_url":"http:\/\/cdn.vistopia.com.cn\/1541733991084.mp3","share_url":"https:\/\/shop.vistopia.com.cn\/article?article_id=51554&share_uid=nZeGt","media_type_en":"audio","content_media_type_en":"audio","type":"charge","content_url":"https:\/\/api.vistopia.com.cn\/api\/v1\/web\/article-content\/vkOcq","sample_media_full_url":"http:\/\/cdn.vistopia.com.cn\/aud\/173399\/043ebf37671b8b362058c732155edd9d.mp3","card_desc":"\u6251\u9762\u800c\u6765\u7684\u547d\u8fd0\uff0c\u662f\u66a7\u6627\u6587\u5316\u8981\u4f60\u53bb\u63a5\u53d7\u7684\u4e8b\u60c5\u3002","is_listened":"0","listen_percent":"0","listen_time":"0","is_finished":"0","is_vip_free":"1","background_img":"http:\/\/cdn.vistopia.com.cn\/1541476786125.jpg","author":"\u5f90\u82f1\u747e","is_vip_only":"0","share_free_count":"10","is_listen":"1"},{"article_id":"56754","content_id":"22","catalog_id":"41","title":"6. \u7269\u54c0\u3001\u4f98\u5bc2\u53ca\u5207\u88c2\uff1a\u6d78\u5165\u5076\u7136\u7684\u5e78\u798f","sort_number":"07","status":"1","share_desc":"\u5728\u7269\u54c0\u3001\u4f98\u5bc2\u53ca\u5207\u88c2\u7684\u5ba1\u7f8e\u4f53\u9a8c\u4e2d\uff0c\u6d78\u5165\u5076\u7136\u7684\u5e78\u798f\u3002","is_trial":"0","duration":"1426","duration_str":"23:46","media_type":"1","media_size":"22314","video_poster":"http:\/\/cdn.vistopia.com.cn\/upload_img.png","comment_count":"82","sample_media_key":"aud\/174715\/50b880a8402482f51f693c133b82673d.mp3","vid":"v03265g10002cccsmgrkutmajrtk16gg","sample_vid":"v0d265g10002ccct5hf8v1n1s3nrddsg","card_data":"","media_key_full_url":"http:\/\/cdn5.vistopia.com.cn\/1541747154269.mp3","optional_media_key_full_url":"http:\/\/cdn.vistopia.com.cn\/1541747154269.mp3","share_url":"https:\/\/shop.vistopia.com.cn\/article?article_id=56754&share_uid=4wqpz","media_type_en":"audio","content_media_type_en":"audio","type":"charge","content_url":"https:\/\/api.vistopia.com.cn\/api\/v1\/web\/article-content\/Fd6Nl","sample_media_full_url":"http:\/\/cdn.vistopia.com.cn\/aud\/174715\/50b880a8402482f51f693c133b82673d.mp3","card_desc":"\u5728\u7269\u54c0\u3001\u4f98\u5bc2\u53ca\u5207\u88c2\u7684\u5ba1\u7f8e\u4f53\u9a8c\u4e2d\uff0c\u6d78\u5165\u5076\u7136\u7684\u5e78\u798f\u3002","is_listened":"0","listen_percent":"0","listen_time":"0","is_finished":"0","is_vip_free":"1","background_img":"http:\/\/cdn.vistopia.com.cn\/1541476786125.jpg","author":"\u5f90\u82f1\u747e","is_vip_only":"0","share_free_count":"10","is_listen":"1"},{"article_id":"57404","content_id":"22","catalog_id":"41","title":"7. \u827a\u4f0e\u6587\u5316\uff1a\u5979\u968f\u98ce\u6613\u901d\uff0c\u5979\u575a\u97e7\u4e0d\u62d4","sort_number":"08","status":"1","share_desc":"\u827a\u4f0e\uff0c\u5973\u7248\u6b66\u58eb\u9053\u3002","is_trial":"0","duration":"1253","duration_str":"20:53","media_type":"1","media_size":"19580","video_poster":"http:\/\/cdn.vistopia.com.cn\/upload_img.png","comment_count":"50","sample_media_key":"aud\/208511\/ceb25a69d0122ced2186068fa3017bbf.mp3","vid":"v03265g10002cccsncqh3be9vs2846k0","sample_vid":"v0d265g10002ccct5i78v1n1s3nrde10","card_data":"","media_key_full_url":"http:\/\/cdn5.vistopia.com.cn\/1542085118689.mp3","optional_media_key_full_url":"http:\/\/cdn.vistopia.com.cn\/1542085118689.mp3","share_url":"https:\/\/shop.vistopia.com.cn\/article?article_id=57404&share_uid=j9fjg","media_type_en":"audio","content_media_type_en":"audio","type":"charge","content_url":"https:\/\/api.vistopia.com.cn\/api\/v1\/web\/article-content\/keJ0z","sample_media_full_url":"http:\/\/cdn.vistopia.com.cn\/aud\/208511\/ceb25a69d0122ced2186068fa3017bbf.mp3","card_desc":"\u827a\u4f0e\uff0c\u5973\u7248\u6b66\u58eb\u9053\u3002","is_listened":"0","listen_percent":"0","listen_time":"0","is_finished":"0","is_vip_free":"1","background_img":"http:\/\/cdn.vistopia.com.cn\/1541476786125.jpg","author":"\u5f90\u82f1\u747e","is_vip_only":"0","share_free_count":"10","is_listen":"1"},{"article_id":"57904","content_id":"22","catalog_id":"41","title":"8. \u201c\u7cb9\u201d\u7684\u4fd7\u6587\u5316\uff1a\u6574\u4e2a\u65e5\u672c\u5c31\u662f\u4e00\u5e45\u753b","sort_number":"09","status":"1","share_desc":"\u8981\u628a\u6bcf\u4e00\u4e2a\u4eba\u5f53\u6210\u753b\u91cc\u7684\u4eba\u6765\u5173\u7167\u3002","is_trial":"0","duration":"1238","duration_str":"20:38","media_type":"1","media_size":"19349","video_poster":"http:\/\/cdn.vistopia.com.cn\/upload_img.png","comment_count":"50","sample_media_key":"aud\/218904\/b7131f438ae4c13876ff4da9605c2f08.mp3","vid":"v03265g10002cccsndlj6f8ur9ie3cf0","sample_vid":"v0d265g10002ccct6d9abc6lp42pid9g","card_data":"","media_key_full_url":"http:\/\/cdn5.vistopia.com.cn\/1542189045029.mp3","optional_media_key_full_url":"http:\/\/cdn.vistopia.com.cn\/1542189045029.mp3","share_url":"https:\/\/shop.vistopia.com.cn\/article?article_id=57904&share_uid=w9rr8","media_type_en":"audio","content_media_type_en":"audio","type":"charge","content_url":"https:\/\/api.vistopia.com.cn\/api\/v1\/web\/article-content\/Fkskw","sample_media_full_url":"http:\/\/cdn.vistopia.com.cn\/aud\/218904\/b7131f438ae4c13876ff4da9605c2f08.mp3","card_desc":"\u8981\u628a\u6bcf\u4e00\u4e2a\u4eba\u5f53\u6210\u753b\u91cc\u7684\u4eba\u6765\u5173\u7167\u3002","is_listened":"0","listen_percent":"0","listen_time":"0","is_finished":"0","is_vip_free":"1","background_img":"http:\/\/cdn.vistopia.com.cn\/1541476786125.jpg","author":"\u5f90\u82f1\u747e","is_vip_only":"0","share_free_count":"10","is_listen":"1"},{"article_id":"58654","content_id":"22","catalog_id":"46","title":"9. \u751f\u6b7b\u66a7\u6627\uff1a\u9b3c\u795e\u5728\u7b2c\u56db\u7ef4\u65f6\u95f4\u91cc","sort_number":"10","status":"1","share_desc":"\u8981\u628a\u6211\u4eec\u7684\u8eab\u4f53\u60f3\u8c61\u6210\u5f25\u6f2b\u5b87\u5b99\u7684\u4e1c\u897f\u3002","is_trial":"0","duration":"1024","duration_str":"17:04","media_type":"1","media_size":"16016","video_poster":"http:\/\/cdn.vistopia.com.cn\/upload_img.png","comment_count":"59","sample_media_key":"aud\/242852\/7e92bc3af26c6d23d10d0db774626521.mp3","vid":"v0d265g10002cccsnef8v1n1s3nrd1rg","sample_vid":"v0d265g10002ccct6e1abc6lp42piddg","card_data":"","media_key_full_url":"http:\/\/cdn5.vistopia.com.cn\/1542428523462.mp3","optional_media_key_full_url":"http:\/\/cdn.vistopia.com.cn\/1542428523462.mp3","share_url":"https:\/\/shop.vistopia.com.cn\/article?article_id=58654&share_uid=6Lln5","media_type_en":"audio","content_media_type_en":"audio","type":"charge","content_url":"https:\/\/api.vistopia.com.cn\/api\/v1\/web\/article-content\/cYuXY","sample_media_full_url":"http:\/\/cdn.vistopia.com.cn\/aud\/242852\/7e92bc3af26c6d23d10d0db774626521.mp3","card_desc":"\u8981\u628a\u6211\u4eec\u7684\u8eab\u4f53\u60f3\u8c61\u6210\u5f25\u6f2b\u5b87\u5b99\u7684\u4e1c\u897f\u3002","is_listened":"0","listen_percent":"0","listen_time":"0","is_finished":"0","is_vip_free":"1","background_img":"http:\/\/cdn.vistopia.com.cn\/1541476786125.jpg","author":"\u5f90\u82f1\u747e","is_vip_only":"0","share_free_count":"10","is_listen":"1"},{"article_id":"59154","content_id":"22","catalog_id":"48","title":"10. \u65e5\u672c\u66a7\u6627\uff0c\u201c\u5929\u65f6\u5730\u5229\u201d","sort_number":"11","status":"1","share_desc":"\u66a7\u6627\uff0c\u662f\u4eba\u7c7b\u7684\u5bbf\u547d\u3002","is_trial":"0","duration":"1102","duration_str":"18:22","media_type":"1","media_size":"17223","video_poster":"http:\/\/cdn.vistopia.com.cn\/upload_img.png","comment_count":"31","sample_media_key":"aud\/268655\/f62f02d658532cf4278ae1b599f765f9.mp3","vid":"v03265g10002cccsneg1rni5du7ccptg","sample_vid":"v0d265g10002ccct6f9abc6lp42pidhg","card_data":"","media_key_full_url":"http:\/\/cdn5.vistopia.com.cn\/1542686551174.mp3","optional_media_key_full_url":"http:\/\/cdn.vistopia.com.cn\/1542686551174.mp3","share_url":"https:\/\/shop.vistopia.com.cn\/article?article_id=59154&share_uid=icnOT","media_type_en":"audio","content_media_type_en":"audio","type":"charge","content_url":"https:\/\/api.vistopia.com.cn\/api\/v1\/web\/article-content\/kV1_7","sample_media_full_url":"http:\/\/cdn.vistopia.com.cn\/aud\/268655\/f62f02d658532cf4278ae1b599f765f9.mp3","card_desc":"\u66a7\u6627\uff0c\u662f\u4eba\u7c7b\u7684\u5bbf\u547d\u3002","is_listened":"0","listen_percent":"0","listen_time":"0","is_finished":"0","is_vip_free":"1","background_img":"http:\/\/cdn.vistopia.com.cn\/1541476786125.jpg","author":"\u5f90\u82f1\u747e","is_vip_only":"0","share_free_count":"10","is_listen":"1"},{"article_id":"59204","content_id":"22","catalog_id":"49","title":"11. \u6d88\u706d\u66a7\u6627\uff0c\u8d70\u5411\u519b\u56fd","sort_number":"12","status":"1","share_desc":"\u66a7\u6627\u662f\u6cbb\u7597\u7cbe\u795e\u72c2\u8e81\u7684\u4e00\u5242\u826f\u836f\u3002","is_trial":"0","duration":"1270","duration_str":"21:10","media_type":"1","media_size":"19848","video_poster":"http:\/\/cdn.vistopia.com.cn\/upload_img.png","comment_count":"52","sample_media_key":"aud\/268847\/7154e1cfaa7a10f4acae22a6894f97b4.mp3","vid":"v03265g10002cccsnf5j6f8ur9ie3ci0","sample_vid":"v0d265g10002ccct6ff8v1n1s3nrdf00","card_data":"","media_key_full_url":"http:\/\/cdn5.vistopia.com.cn\/1542688470181.mp3","optional_media_key_full_url":"http:\/\/cdn.vistopia.com.cn\/1542688470181.mp3","share_url":"https:\/\/shop.vistopia.com.cn\/article?article_id=59204&share_uid=dEDcO","media_type_en":"audio","content_media_type_en":"audio","type":"charge","content_url":"https:\/\/api.vistopia.com.cn\/api\/v1\/web\/article-content\/nHk2F","sample_media_full_url":"http:\/\/cdn.vistopia.com.cn\/aud\/268847\/7154e1cfaa7a10f4acae22a6894f97b4.mp3","card_desc":"\u66a7\u6627\u662f\u6cbb\u7597\u7cbe\u795e\u72c2\u8e81\u7684\u4e00\u5242\u826f\u836f\u3002","is_listened":"0","listen_percent":"0","listen_time":"0","is_finished":"0","is_vip_free":"1","background_img":"http:\/\/cdn.vistopia.com.cn\/1541476786125.jpg","author":"\u5f90\u82f1\u747e","is_vip_only":"0","share_free_count":"10","is_listen":"1"},{"article_id":"67404","content_id":"22","catalog_id":"68","title":"12. \u751f\u6d3b\u4e0d\u5e78\u7684\u4eba\uff0c\u5199\u7684\u4e66\u4e5f\u6bd4\u8f83\u96be\u8bfb","sort_number":"13","status":"1","share_desc":"\u4eac\u90fd\u5b66\u6d3e\u638c\u95e8\u4eba\u897f\u7530\u51e0\u591a\u90ce\uff0c\u5176\u5b9e\u662f\u4e2a\u6c11\u54f2\uff1f","is_trial":"1","duration":"179","duration_str":"02:59","media_type":"1","media_size":"2809","video_poster":"http:\/\/cdn.vistopia.com.cn\/upload_img.png","comment_count":"14","sample_media_key":"aud\/504352\/e4d386db4624a5441db540af6a0f010a.mp3","vid":"v03265g10002cccsr5o1rni5du7ccqn0","sample_vid":"v0d265g10002ccct99v8v1n1s3nrdi50","card_data":"","media_key_full_url":"http:\/\/cdn5.vistopia.com.cn\/1545043521366.mp3","optional_media_key_full_url":"http:\/\/cdn.vistopia.com.cn\/1545043521366.mp3","share_url":"https:\/\/shop.vistopia.com.cn\/article?article_id=67404","media_type_en":"audio","content_media_type_en":"audio","type":"charge","content_url":"https:\/\/api.vistopia.com.cn\/api\/v1\/web\/article-content\/hQYot","sample_media_full_url":"http:\/\/cdn.vistopia.com.cn\/aud\/504352\/e4d386db4624a5441db540af6a0f010a.mp3","card_desc":"\u4eac\u90fd\u5b66\u6d3e\u638c\u95e8\u4eba\u897f\u7530\u51e0\u591a\u90ce\uff0c\u5176\u5b9e\u662f\u4e2a\u6c11\u54f2\uff1f","is_listened":"0","listen_percent":"0","listen_time":"0","is_finished":"0","is_vip_free":"1","background_img":"http:\/\/cdn.vistopia.com.cn\/1541476786125.jpg","author":"\u5f90\u82f1\u747e","is_vip_only":"0","share_free_count":"0","is_listen":"1"},{"article_id":"67454","content_id":"22","catalog_id":"68","title":"13. \u6d77\u5fb7\u683c\u5c14\u6709\u53cd\u72b9\u503e\u5411\uff1f","sort_number":"14","status":"1","share_desc":"\u6d77\u5fb7\u683c\u5c14\u65e5\u8bb0\u3002","is_trial":"0","duration":"43","duration_str":"00:43","media_type":"1","media_size":"675","video_poster":"http:\/\/cdn.vistopia.com.cn\/upload_img.png","comment_count":"1","sample_media_key":"aud\/504450\/b5a1102f1042ef76b4f1a6166dd64e13.mp3","vid":"v03265g10002cccsr5qh3be9vs2847cg","sample_vid":"v0d265g10002ccct99habc6lp42pighg","card_data":"","media_key_full_url":"http:\/\/cdn5.vistopia.com.cn\/1545044504389.mp3","optional_media_key_full_url":"http:\/\/cdn.vistopia.com.cn\/1545044504389.mp3","share_url":"https:\/\/shop.vistopia.com.cn\/article?article_id=67454&share_uid=w9rr8","media_type_en":"audio","content_media_type_en":"audio","type":"charge","content_url":"https:\/\/api.vistopia.com.cn\/api\/v1\/web\/article-content\/oh4P9","sample_media_full_url":"http:\/\/cdn.vistopia.com.cn\/aud\/504450\/b5a1102f1042ef76b4f1a6166dd64e13.mp3","card_desc":"\u6d77\u5fb7\u683c\u5c14\u65e5\u8bb0\u3002","is_listened":"0","listen_percent":"0","listen_time":"0","is_finished":"0","is_vip_free":"1","background_img":"http:\/\/cdn.vistopia.com.cn\/1541476786125.jpg","author":"\u5f90\u82f1\u747e","is_vip_only":"0","share_free_count":"10","is_listen":"1"},{"article_id":"67504","content_id":"22","catalog_id":"68","title":"14. \u66a7\u6627\u4f1a\u5bfc\u81f4\u4e2a\u6027\u7684\u538b\u6291\uff1f","sort_number":"15","status":"1","share_desc":"\u65e5\u672c\u4eba\u628a\u96c6\u4f53\u770b\u5f97\u592a\u91cd\uff0c\u4ea7\u751f\u77db\u76fe\u4e86\uff0c\u81ea\u5df1\u8df3\u697c\u3002","is_trial":"1","duration":"101","duration_str":"01:41","media_type":"1","media_size":"1594","video_poster":"http:\/\/cdn.vistopia.com.cn\/upload_img.png","comment_count":"4","sample_media_key":"aud\/504623\/639350851bfbcc8edb9e84416d502b6c.mp3","vid":"v02265g10002cccsr5r0h3e41t2etk8g","sample_vid":"v0d265g10002ccct9af8v1n1s3nrdi9g","card_data":"","media_key_full_url":"http:\/\/cdn5.vistopia.com.cn\/1545046230347.mp3","optional_media_key_full_url":"http:\/\/cdn.vistopia.com.cn\/1545046230347.mp3","share_url":"https:\/\/shop.vistopia.com.cn\/article?article_id=67504","media_type_en":"audio","content_media_type_en":"audio","type":"charge","content_url":"https:\/\/api.vistopia.com.cn\/api\/v1\/web\/article-content\/uq9z_","sample_media_full_url":"http:\/\/cdn.vistopia.com.cn\/aud\/504623\/639350851bfbcc8edb9e84416d502b6c.mp3","card_desc":"\u65e5\u672c\u4eba\u628a\u96c6\u4f53\u770b\u5f97\u592a\u91cd\uff0c\u4ea7\u751f\u77db\u76fe\u4e86\uff0c\u81ea\u5df1\u8df3\u697c\u3002","is_listened":"0","listen_percent":"0","listen_time":"0","is_finished":"0","is_vip_free":"1","background_img":"http:\/\/cdn.vistopia.com.cn\/1541476786125.jpg","author":"\u5f90\u82f1\u747e","is_vip_only":"0","share_free_count":"0","is_listen":"1"},{"article_id":"67704","content_id":"22","catalog_id":"68","title":"15. \u4e5d\u9b3c\u5468\u9020\uff1a\u8d8a\u89c1\u4eba\u95f4\u7f8e\u8272\uff0c\u8fd8\u662f\u65e5\u672c\u5973\u5b69\u597d","sort_number":"16","status":"1","share_desc":"\u5e38\u53bb\u7ea2\u706f\u533a\uff0c\u8fd9\u662f\u4e5d\u9b3c\u5468\u9020\u7684\u6d6a\u6f2b\uff1f","is_trial":"0","duration":"146","duration_str":"02:26","media_type":"1","media_size":"2286","video_poster":"http:\/\/cdn.vistopia.com.cn\/upload_img.png","comment_count":"6","sample_media_key":"aud\/510454\/b07795872927e8d9f2b91c770cfbb209.mp3","vid":"v02265g10002cccsr60mjg8vbhnsm4eg","sample_vid":"v0d265g10002cccta4pabc6lp42pih7g","card_data":"","media_key_full_url":"http:\/\/cdn5.vistopia.com.cn\/1545104543193.mp3","optional_media_key_full_url":"http:\/\/cdn.vistopia.com.cn\/1545104543193.mp3","share_url":"https:\/\/shop.vistopia.com.cn\/article?article_id=67704&share_uid=3rKfW","media_type_en":"audio","content_media_type_en":"audio","type":"charge","content_url":"https:\/\/api.vistopia.com.cn\/api\/v1\/web\/article-content\/kN3d4","sample_media_full_url":"http:\/\/cdn.vistopia.com.cn\/aud\/510454\/b07795872927e8d9f2b91c770cfbb209.mp3","card_desc":"\u5e38\u53bb\u7ea2\u706f\u533a\uff0c\u8fd9\u662f\u4e5d\u9b3c\u5468\u9020\u7684\u6d6a\u6f2b\uff1f","is_listened":"0","listen_percent":"0","listen_time":"0","is_finished":"0","is_vip_free":"1","background_img":"http:\/\/cdn.vistopia.com.cn\/1541476786125.jpg","author":"\u5f90\u82f1\u747e","is_vip_only":"0","share_free_count":"10","is_listen":"1"},{"article_id":"67754","content_id":"22","catalog_id":"68","title":"16. \u5fb7\u5ddd\u5bb6\u5eb7\uff1a\u7a7f\u91d1\u6234\u94f6\u662f\u683c\u8c03\u5f88\u4f4e\u7684\u4e8b","sort_number":"17","status":"1","share_desc":"\u4e30\u7530\u79c0\u5409\u6bd4\u8f83\u50cf\u6731\u5143\u748b\uff0c\u5f97\u52bf\u4e4b\u540e\u6068\u4e0d\u5f97\u7259\u90fd\u9576\u6210\u91d1\u7684\u3002","is_trial":"0","duration":"155","duration_str":"02:35","media_type":"1","media_size":"2438","video_poster":"http:\/\/cdn.vistopia.com.cn\/upload_img.png","comment_count":"4","sample_media_key":"aud\/510693\/a471235ba285b6c8239fa4371c7a691f.mp3","vid":"v02265g10002cccsr60mjg8vbhnsm4f0","sample_vid":"v0d265g10002cccta51abc6lp42pih8g","card_data":"","media_key_full_url":"http:\/\/cdn5.vistopia.com.cn\/1545106939315.mp3","optional_media_key_full_url":"http:\/\/cdn.vistopia.com.cn\/1545106939315.mp3","share_url":"https:\/\/shop.vistopia.com.cn\/article?article_id=67754&share_uid=lZBoz","media_type_en":"audio","content_media_type_en":"audio","type":"charge","content_url":"https:\/\/api.vistopia.com.cn\/api\/v1\/web\/article-content\/Uqiew","sample_media_full_url":"http:\/\/cdn.vistopia.com.cn\/aud\/510693\/a471235ba285b6c8239fa4371c7a691f.mp3","card_desc":"\u4e30\u7530\u79c0\u5409\u6bd4\u8f83\u50cf\u6731\u5143\u748b\uff0c\u5f97\u52bf\u4e4b\u540e\u6068\u4e0d\u5f97\u7259\u90fd\u9576\u6210\u91d1\u7684\u3002","is_listened":"0","listen_percent":"0","listen_time":"0","is_finished":"0","is_vip_free":"1","background_img":"http:\/\/cdn.vistopia.com.cn\/1541476786125.jpg","author":"\u5f90\u82f1\u747e","is_vip_only":"0","share_free_count":"10","is_listen":"1"},{"article_id":"67804","content_id":"22","catalog_id":"68","title":"17. \u4e30\u81e3\u79c0\u5409\uff1a\u6211\u5f88\u614c\u554a\uff0c\u7a7f\u91d1\u6234\u94f6\u6211\u8fd8\u80fd\u7a33\u70b9","sort_number":"18","status":"1","share_desc":"\u989c\u8272\u91cc\uff0c\u8fd8\u9690\u85cf\u7740\u8eab\u4efd\u8ba4\u540c\u7684\u4fe1\u606f\u3002","is_trial":"0","duration":"130","duration_str":"02:10","media_type":"1","media_size":"2042","video_poster":"http:\/\/cdn.vistopia.com.cn\/upload_img.png","comment_count":"4","sample_media_key":"aud\/510815\/60bb2acff11ff21f8edf18559d28aebc.mp3","vid":"v02265g10002cccsr60ijgv73ie34240","sample_vid":"v0d265g10002cccta4pabc6lp42pih70","card_data":"","media_key_full_url":"http:\/\/cdn5.vistopia.com.cn\/1545108150162.mp3","optional_media_key_full_url":"http:\/\/cdn.vistopia.com.cn\/1545108150162.mp3","share_url":"https:\/\/shop.vistopia.com.cn\/article?article_id=67804&share_uid=fkuE1","media_type_en":"audio","content_media_type_en":"audio","type":"charge","content_url":"https:\/\/api.vistopia.com.cn\/api\/v1\/web\/article-content\/dY9M2","sample_media_full_url":"http:\/\/cdn.vistopia.com.cn\/aud\/510815\/60bb2acff11ff21f8edf18559d28aebc.mp3","card_desc":"\u989c\u8272\u91cc\uff0c\u8fd8\u9690\u85cf\u7740\u8eab\u4efd\u8ba4\u540c\u7684\u4fe1\u606f\u3002","is_listened":"0","listen_percent":"0","listen_time":"0","is_finished":"0","is_vip_free":"1","background_img":"http:\/\/cdn.vistopia.com.cn\/1541476786125.jpg","author":"\u5f90\u82f1\u747e","is_vip_only":"0","share_free_count":"10","is_listen":"1"},{"article_id":"67854","content_id":"22","catalog_id":"68","title":"18. \u91d1\u9601\u5bfa\u592a\u62db\u6447","sort_number":"19","status":"1","share_desc":"\u91d1\u9601\u5bfa\u3001\u94f6\u9601\u5bfa\uff0c\u54ea\u4e2a\u4f60\u66f4\u7231\uff1f","is_trial":"0","duration":"85","duration_str":"01:25","media_type":"1","media_size":"1338","video_poster":"http:\/\/cdn.vistopia.com.cn\/upload_img.png","comment_count":"3","sample_media_key":"aud\/510966\/e4b59f5d9ec7dbd60e91b8ce13130bd8.mp3","vid":"v02265g10002cccsr62uktkhvr2l7p4g","sample_vid":"v0d265g10002cccta51abc6lp42pih80","card_data":"","media_key_full_url":"http:\/\/cdn5.vistopia.com.cn\/1545109664265.mp3","optional_media_key_full_url":"http:\/\/cdn.vistopia.com.cn\/1545109664265.mp3","share_url":"https:\/\/shop.vistopia.com.cn\/article?article_id=67854&share_uid=TXniw","media_type_en":"audio","content_media_type_en":"audio","type":"charge","content_url":"https:\/\/api.vistopia.com.cn\/api\/v1\/web\/article-content\/ODcUP","sample_media_full_url":"http:\/\/cdn.vistopia.com.cn\/aud\/510966\/e4b59f5d9ec7dbd60e91b8ce13130bd8.mp3","card_desc":"\u91d1\u9601\u5bfa\u3001\u94f6\u9601\u5bfa\uff0c\u54ea\u4e2a\u4f60\u66f4\u7231\uff1f","is_listened":"0","listen_percent":"0","listen_time":"0","is_finished":"0","is_vip_free":"1","background_img":"http:\/\/cdn.vistopia.com.cn\/1541476786125.jpg","author":"\u5f90\u82f1\u747e","is_vip_only":"0","share_free_count":"10","is_listen":"1"},{"article_id":"67904","content_id":"22","catalog_id":"68","title":"19. \u4e5d\u9b3c\uff0c\u4f60\u51fa\u751f\u65f6\u6709\u4e5d\u4e2a\u5c0f\u5929\u4f7f\u5728\u4f60\u5468\u56f4\u5417\uff1f","sort_number":"20","status":"1","share_desc":"\u4e5d\u9b3c\u6bcf\u6b21\u4f4f\u56fd\u5916\u9152\u5e97\uff0c\u4eba\u5bb6\u90fd\u8bf4\uff0c\u66f2\u5947\u6765\u4e86\u3002","is_trial":"0","duration":"170","duration_str":"02:50","media_type":"1","media_size":"2665","video_poster":"http:\/\/cdn.vistopia.com.cn\/upload_img.png","comment_count":"5","sample_media_key":"aud\/511666\/bb3b8eb0ae9c371adc95c4a54b0a959e.mp3","vid":"v03265g10002cccsr681rni5du7ccqog","sample_vid":"v0d265g10002cccta578v1n1s3nrdipg","card_data":"","media_key_full_url":"http:\/\/cdn5.vistopia.com.cn\/1545116666443.mp3","optional_media_key_full_url":"http:\/\/cdn.vistopia.com.cn\/1545116666443.mp3","share_url":"https:\/\/shop.vistopia.com.cn\/article?article_id=67904&share_uid=4wqpz","media_type_en":"audio","content_media_type_en":"audio","type":"charge","content_url":"https:\/\/api.vistopia.com.cn\/api\/v1\/web\/article-content\/OaJO9","sample_media_full_url":"http:\/\/cdn.vistopia.com.cn\/aud\/511666\/bb3b8eb0ae9c371adc95c4a54b0a959e.mp3","card_desc":"\u4e5d\u9b3c\u6bcf\u6b21\u4f4f\u56fd\u5916\u9152\u5e97\uff0c\u4eba\u5bb6\u90fd\u8bf4\uff0c\u66f2\u5947\u6765\u4e86\u3002","is_listened":"0","listen_percent":"0","listen_time":"0","is_finished":"0","is_vip_free":"1","background_img":"http:\/\/cdn.vistopia.com.cn\/1541476786125.jpg","author":"\u5f90\u82f1\u747e","is_vip_only":"0","share_free_count":"10","is_listen":"1"},{"article_id":"67954","content_id":"22","catalog_id":"68","title":"20. \u827a\u672f\u5de8\u5320\u5188\u4ed3\u5929\u5fc3\u662f\u4e5d\u9b3c\u5468\u9020\u5988\u54aa\u7684\u7537\u670b\u53cb\uff1f","sort_number":"21","status":"1","share_desc":"\u4e5d\u9b3c\u5468\u9020\u7edd\u5bf9\u914d\u59d3\u4e5d\u9b3c\u3002","is_trial":"0","duration":"140","duration_str":"02:20","media_type":"1","media_size":"2203","video_poster":"http:\/\/cdn.vistopia.com.cn\/upload_img.png","comment_count":"20","sample_media_key":"aud\/511835\/a5f08aee80146c27e598f53783bd8c87.mp3","vid":"v02265g10002cccsr6b0h3e41t2etk9g","sample_vid":"v0d265g10002cccta59abc6lp42pih9g","card_data":"","media_key_full_url":"http:\/\/cdn5.vistopia.com.cn\/1545118357289.mp3","optional_media_key_full_url":"http:\/\/cdn.vistopia.com.cn\/1545118357289.mp3","share_url":"https:\/\/shop.vistopia.com.cn\/article?article_id=67954&share_uid=aGDVl","media_type_en":"audio","content_media_type_en":"audio","type":"charge","content_url":"https:\/\/api.vistopia.com.cn\/api\/v1\/web\/article-content\/6HqLp","sample_media_full_url":"http:\/\/cdn.vistopia.com.cn\/aud\/511835\/a5f08aee80146c27e598f53783bd8c87.mp3","card_desc":"\u4e5d\u9b3c\u5468\u9020\u7edd\u5bf9\u914d\u59d3\u4e5d\u9b3c\u3002","is_listened":"0","listen_percent":"0","listen_time":"0","is_finished":"0","is_vip_free":"1","background_img":"http:\/\/cdn.vistopia.com.cn\/1541476786125.jpg","author":"\u5f90\u82f1\u747e","is_vip_only":"0","share_free_count":"10","is_listen":"1"},{"article_id":"85895","content_id":"22","catalog_id":"68","title":"21. \u5728\u65e5\u672c\uff0c\u53ef\u7231\u662f\u5973\u5b69\u7684\u7075\u9b42 | \u5927\u5185\u5bc6\u8c08","sort_number":"22","status":"1","share_desc":"\u65e5\u672c\u662f\u5904\u5973\u5ea7\u7684\u3002","is_trial":"1","duration":"4133","duration_str":"01:08:53","media_type":"1","media_size":"64581","video_poster":"http:\/\/cdn.vistopia.com.cn\/upload_img.png","comment_count":"231","sample_media_key":"aud\/037584\/15daf065561416e86c16400dc6e529ac.mp3","vid":"v0d265g10002ccct1ov8v1n1s3nrda0g","sample_vid":"v0d265g10002ccctg51abc6lp42pir90","card_data":"","media_key_full_url":"http:\/\/cdn5.vistopia.com.cn\/1550375849555.mp3","optional_media_key_full_url":"http:\/\/cdn.vistopia.com.cn\/1550375849555.mp3","share_url":"https:\/\/shop.vistopia.com.cn\/article?article_id=85895","media_type_en":"audio","content_media_type_en":"audio","type":"charge","content_url":"https:\/\/api.vistopia.com.cn\/api\/v1\/web\/article-content\/gkL7D","sample_media_full_url":"http:\/\/cdn.vistopia.com.cn\/aud\/037584\/15daf065561416e86c16400dc6e529ac.mp3","card_desc":"\u65e5\u672c\u662f\u5904\u5973\u5ea7\u7684\u3002","is_listened":"0","listen_percent":"0","listen_time":"0","is_finished":"0","is_vip_free":"1","background_img":"http:\/\/cdn.vistopia.com.cn\/1541476786125.jpg","author":"\u5f90\u82f1\u747e","is_vip_only":"0","share_free_count":"0","is_listen":"1"},{"article_id":"250690","content_id":"22","catalog_id":"68","title":"22. \u75ab\u60c5\u671f\u95f4\u5982\u4f55\u50cf\u54f2\u5b66\u5bb6\u4e00\u6837\u601d\u8003 | 3.23\u76f4\u64ad\u9884\u544a","sort_number":"23","status":"1","share_desc":"\u54d4\u54e9\u54d4\u54e9#\u770b\u7406\u60f3vistopia\uff0c3.23\u665a8\u3002","is_trial":"0","duration":"255","duration_str":"04:15","media_type":"1","media_size":"5988","video_poster":"http:\/\/cdn.vistopia.com.cn\/upload_img.png","comment_count":"36","sample_media_key":"aud\/467458\/4dc60c61c07b658b44d97869acf20835.mp3","vid":"v03265g10002ccd9u8jkutmajrtk48tg","sample_vid":"v0d265g10002ccdalkv8v1n1s3nrkd7g","card_data":"","media_key_full_url":"http:\/\/cdn5.vistopia.com.cn\/1584674584161.mp3","optional_media_key_full_url":"http:\/\/cdn.vistopia.com.cn\/1584674584161.mp3","share_url":"https:\/\/shop.vistopia.com.cn\/article?article_id=250690&share_uid=zG5v6","media_type_en":"audio","content_media_type_en":"audio","type":"charge","content_url":"https:\/\/api.vistopia.com.cn\/api\/v1\/web\/article-content\/jsiDJ","sample_media_full_url":"http:\/\/cdn.vistopia.com.cn\/aud\/467458\/4dc60c61c07b658b44d97869acf20835.mp3","card_desc":"","is_listened":"0","listen_percent":"0","listen_time":"0","is_finished":"0","is_vip_free":"1","background_img":"http:\/\/cdn.vistopia.com.cn\/1541476786125.jpg","author":"\u5f90\u82f1\u747e","is_vip_only":"0","share_free_count":"10","is_listen":"1"}]}}