{"status":"success","data":{"content":{"content_id":"233","title":"\u5982\u4f55\u542c\u61c2\u8096\u90a6\uff1a\u7126\u5143\u6ea5\u8096\u90a610\u8bb2","small_background_img":"http:\/\/cdn.vistopia.com.cn\/1632992965057.png","background_img":"http:\/\/cdn.vistopia.com.cn\/1632992960393.png","catalog_type":"1","type":"charge","complete_class_price":"48.00","promotion_price":"28.00","promotion_desc":"","is_promotion":"1","media_type":"1","is_vip_free":"1","is_vip_only":"0","avatar":"http:\/\/cdn.vistopia.com.cn\/1535338211116.jpg","text_desc":"\u77e5\u540d\u53e4\u5178\u97f3\u4e50\u4e50\u8bc4\u4eba\u3001\u97f3\u4e50\u4f1a\u7b56\u5212\u4eba","media_type_en":"audio","author":"\u7126\u5143\u6ea5","is_purchased":"0","is_subscribed":"0","vip_type":"lixiangjia_trial","is_vip_expired":"0","old_vip_type":"","is_limited_free":"0"},"catalogs":[{"catalog_id":"1051","catalog_title":"\u8096\u90a6\u5341\u8bb2"}],"articles":[{"article_id":"474894","content_id":"233","catalog_id":"1051","title":"01. \u96f6\u57fa\u7840\u5165\u95e8\uff1a\u5927\u5bb6\u90fd\u7231\u8096\u90a6\u5417\uff1f","sort_number":"01","status":"1","share_desc":"\u300a\u5982\u4f55\u542c\u61c2\u8096\u90a6\uff1a\u7126\u5143\u6ea5\u8096\u90a610\u8bb2\u300b","is_trial":"1","duration":"1609","duration_str":"26:49","media_type":"1","media_size":"25345","video_poster":"http:\/\/cdn.vistopia.com.cn\/upload_img.png","comment_count":"62","sample_media_key":"aud\/9be93-\/2b912a5e980fbe0d2fd599d9d5865c5a.mp3","vid":"v03265g10002ccdb63rkutmajrtk4m40","sample_vid":"v0d265g10002ccdvvmv8v1n1s3nrunfg","card_data":"","media_key_full_url":"http:\/\/cdn.vistopia.com.cn\/dd49be93-ae2a-484f-95cd-6f12a3eb3121.mp3","optional_media_key_full_url":"http:\/\/cdn5.vistopia.com.cn\/dd49be93-ae2a-484f-95cd-6f12a3eb3121.mp3","share_url":"https:\/\/shop.vistopia.com.cn\/article?article_id=474894","media_type_en":"audio","content_media_type_en":"audio","type":"charge","content_url":"https:\/\/api.vistopia.com.cn\/api\/v1\/web\/article-content\/K5rMi","sample_media_full_url":"http:\/\/cdn.vistopia.com.cn\/aud\/9be93-\/2b912a5e980fbe0d2fd599d9d5865c5a.mp3","card_desc":"\u8981\u5f39\u597d\u8096\u90a6\u5b9e\u5728\u662f\u4e0d\u5bb9\u6613\uff0c\u8fd9\u4e2a\u4e0d\u5bb9\u6613\u4e0d\u6b62\u6765\u81ea\u4e8e\u94a2\u7434\u6280\u672f\u4e0a\u7684\u6311\u6218\uff0c\u8fd8\u6765\u81ea\u4e8e\u4f60\u5bf9\u8096\u90a6\u97f3\u4e50\u7684\u7406\u89e3\uff0c\u4ee5\u53ca\u5404\u79cd\u98ce\u683c\u7684\u638c\u63e1\u548c\u8c03\u914d\u3002","is_listened":"0","listen_percent":"0","listen_time":"0","is_finished":"0","is_vip_free":"1","background_img":"http:\/\/cdn.vistopia.com.cn\/1632992960393.png","author":"\u7126\u5143\u6ea5","is_vip_only":"0","share_free_count":"0","is_listen":"1"},{"article_id":"474944","content_id":"233","catalog_id":"1051","title":"02. \u7edd\u4e16\u5929\u624d\u7684\u8bde\u751f\uff1a\u8096\u90a6\u662f\u600e\u4e48\u7ec3\u6210\u7684","sort_number":"02","status":"1","share_desc":"\u300a\u5982\u4f55\u542c\u61c2\u8096\u90a6\uff1a\u7126\u5143\u6ea5\u8096\u90a610\u8bb2\u300b","is_trial":"0","duration":"1899","duration_str":"31:39","media_type":"1","media_size":"29694","video_poster":"http:\/\/cdn.vistopia.com.cn\/upload_img.png","comment_count":"46","sample_media_key":"aud\/b42a4-\/8b94cb7506b4bb318a225db695c68a9f.mp3","vid":"v03265g10002ccdb63tj6f8ur9ie76m0","sample_vid":"v0d265g10002cce0059abc6lp42q4cl0","card_data":"","media_key_full_url":"http:\/\/cdn.vistopia.com.cn\/e87b42a4-e8f0-46d3-8135-6b94f21486d6.mp3","optional_media_key_full_url":"http:\/\/cdn5.vistopia.com.cn\/e87b42a4-e8f0-46d3-8135-6b94f21486d6.mp3","share_url":"https:\/\/shop.vistopia.com.cn\/article?article_id=474944&share_uid=MJjyY","media_type_en":"audio","content_media_type_en":"audio","type":"charge","content_url":"https:\/\/api.vistopia.com.cn\/api\/v1\/web\/article-content\/lt_ZS","sample_media_full_url":"http:\/\/cdn.vistopia.com.cn\/aud\/b42a4-\/8b94cb7506b4bb318a225db695c68a9f.mp3","card_desc":"\u5982\u679c\u8096\u90a6\u81ea\u5df1\u6765\u53c2\u52a0\u8096\u90a6\u94a2\u7434\u5927\u8d5b\uff0c\u4f1a\u5f97\u51a0\u519b\u5417\uff1f","is_listened":"0","listen_percent":"0","listen_time":"0","is_finished":"0","is_vip_free":"1","background_img":"http:\/\/cdn.vistopia.com.cn\/1632992960393.png","author":"\u7126\u5143\u6ea5","is_vip_only":"0","share_free_count":"10","is_listen":"1"},{"article_id":"478244","content_id":"233","catalog_id":"1051","title":"03. \u53cb\u60c5\u4e0e\u7231\u60c5\uff1a\u8096\u90a6\u4e0e\u4e54\u6cbb\u00b7\u6851\u7684\u611f\u60c5\u4e16\u754c","sort_number":"03","status":"1","share_desc":"\u300a\u5982\u4f55\u542c\u61c2\u8096\u90a6\uff1a\u7126\u5143\u6ea5\u8096\u90a610\u8bb2\u300b","is_trial":"1","duration":"1638","duration_str":"27:18","media_type":"1","media_size":"25647","video_poster":"http:\/\/cdn.vistopia.com.cn\/upload_img.png","comment_count":"25","sample_media_key":"aud\/64867-\/7cd4550c5d310ef153b704b6b8177b45.mp3","vid":"v03265g10002ccdb6jhb0aqvkobpolu0","sample_vid":"v0d265g10002cce0rrhabc6lp42q4qp0","card_data":"","media_key_full_url":"http:\/\/cdn.vistopia.com.cn\/bbc64867-94db-4d22-b29d-1406e205284e.mp3","optional_media_key_full_url":"http:\/\/cdn5.vistopia.com.cn\/bbc64867-94db-4d22-b29d-1406e205284e.mp3","share_url":"https:\/\/shop.vistopia.com.cn\/article?article_id=478244","media_type_en":"audio","content_media_type_en":"audio","type":"charge","content_url":"https:\/\/api.vistopia.com.cn\/api\/v1\/web\/article-content\/Bts7y","sample_media_full_url":"http:\/\/cdn.vistopia.com.cn\/aud\/64867-\/7cd4550c5d310ef153b704b6b8177b45.mp3","card_desc":"\u5728\u611f\u60c5\u4e4b\u4e2d\u5f88\u96be\u8bf4\u6709\u4ec0\u4e48\u5bf9\u9519\uff0c\u5982\u679c\u5927\u5bb6\u6709\u673a\u4f1a\uff0c\u4e0d\u59a8\u5230\u6cd5\u56fd\u8bfa\u6602\u4e54\u6cbb\u00b7\u6851\u6545\u5c45\uff0c\u770b\u770b\u5f53\u5e74\u5979\u8ddf\u8096\u90a6\u751f\u6d3b\u7684\u5730\u65b9\u3002\u5728\u90a3\u91cc\uff0c\u5979\u4e3a\u5979\u7684\u513f\u5973\u5404\u79cd\u4e0b\u4e00\u68f5\u6811\uff0c\u8fd9\u4e24\u68f5\u6811\u81f3\u4eca\u72b9\u5728\uff0c\u89c1\u8bc1\u4e86\u6240\u6709\u98ce\u971c\u3002","is_listened":"0","listen_percent":"0","listen_time":"0","is_finished":"0","is_vip_free":"1","background_img":"http:\/\/cdn.vistopia.com.cn\/1632992960393.png","author":"\u7126\u5143\u6ea5","is_vip_only":"0","share_free_count":"0","is_listen":"1"},{"article_id":"480444","content_id":"233","catalog_id":"1051","title":"04. \u6c11\u65cf\u4e3b\u4e49\u4e0e\u670b\u53cb\u5708\uff1a\u8096\u90a6\u662f\u201c\u7231\u56fd\u8bd7\u4eba\u201d\u5417\uff1f","sort_number":"04","status":"1","share_desc":"\u300a\u5982\u4f55\u542c\u61c2\u8096\u90a6\uff1a\u7126\u5143\u6ea5\u8096\u90a610\u8bb2\u300b","is_trial":"0","duration":"1779","duration_str":"29:39","media_type":"1","media_size":"27836","video_poster":"http:\/\/cdn.vistopia.com.cn\/upload_img.png","comment_count":"17","sample_media_key":"aud\/6ae81-\/369f5dd9fd41fe195befa75f920bc7ed.mp3","vid":"v03265g10002ccdb722oktor4971j0g0","sample_vid":"v0d265g10002cce1e378v1n1s3nrvaq0","card_data":"","media_key_full_url":"http:\/\/cdn.vistopia.com.cn\/d8e6ae81-3982-46fb-80cc-99bd09d9efc2.mp3","optional_media_key_full_url":"http:\/\/cdn5.vistopia.com.cn\/d8e6ae81-3982-46fb-80cc-99bd09d9efc2.mp3","share_url":"https:\/\/shop.vistopia.com.cn\/article?article_id=480444&share_uid=DIag9","media_type_en":"audio","content_media_type_en":"audio","type":"charge","content_url":"https:\/\/api.vistopia.com.cn\/api\/v1\/web\/article-content\/u0Ze3","sample_media_full_url":"http:\/\/cdn.vistopia.com.cn\/aud\/6ae81-\/369f5dd9fd41fe195befa75f920bc7ed.mp3","card_desc":"\u8096\u90a6\u5f53\u7136\u4e0d\u4f1a\u5b8c\u5168\u4e0d\u548c\u4ed6\u7684\u65f6\u4ee3\u4e92\u52a8\uff0c\u8fd9\u662f\u4e0d\u53ef\u80fd\u7684\uff0c\u8096\u90a6\u6bd5\u7adf\u4e5f\u662f\u4e00\u4e2a\u5438\u6536\u5404\u79cd\u5143\u7d20\u7684\u827a\u672f\u5bb6\u3002\u4f46\u4ed6\u51e0\u4e4e\u662f\u51b7\u773c\u65c1\u89c2\uff0c\u5f88\u96be\u79f0\u5f97\u4e0a\u7275\u626f\u5165\u4efb\u4f55\u201c\u521b\u4f5c\u4e3b\u4e49\u201d\u6216\u8005\u662f\u201c\u65f6\u4ee3\u98ce\u6f6e\u201d\u3002","is_listened":"0","listen_percent":"0","listen_time":"0","is_finished":"0","is_vip_free":"1","background_img":"http:\/\/cdn.vistopia.com.cn\/1632992960393.png","author":"\u7126\u5143\u6ea5","is_vip_only":"0","share_free_count":"10","is_listen":"1"},{"article_id":"480644","content_id":"233","catalog_id":"1051","title":"05. \u50b2\u6162\u4e0e\u4f20\u627f\uff1a\u8096\u90a6\u5982\u4f55\u770b\u5f85\u5df4\u8d6b\u3001\u83ab\u624e\u7279\u4e0e\u8d1d\u591a\u82ac","sort_number":"06","status":"1","share_desc":"\u300a\u5982\u4f55\u542c\u61c2\u8096\u90a6\uff1a\u7126\u5143\u6ea5\u8096\u90a610\u8bb2\u300b","is_trial":"0","duration":"1564","duration_str":"26:04","media_type":"1","media_size":"24491","video_poster":"http:\/\/cdn.vistopia.com.cn\/upload_img.png","comment_count":"12","sample_media_key":"aud\/36b56-\/147e4530784fb0a92b81d6ff4b0e610e.mp3","vid":"v03265g10002ccdb723ghao71ec23ds0","sample_vid":"v0d265g10002cce1fvn8v1n1s3nrvd10","card_data":"","media_key_full_url":"http:\/\/cdn.vistopia.com.cn\/5b036b56-953e-44f2-8288-14f0699e7c10.mp3","optional_media_key_full_url":"http:\/\/cdn5.vistopia.com.cn\/5b036b56-953e-44f2-8288-14f0699e7c10.mp3","share_url":"https:\/\/shop.vistopia.com.cn\/article?article_id=480644&share_uid=gkPtr","media_type_en":"audio","content_media_type_en":"audio","type":"charge","content_url":"https:\/\/api.vistopia.com.cn\/api\/v1\/web\/article-content\/EALWd","sample_media_full_url":"http:\/\/cdn.vistopia.com.cn\/aud\/36b56-\/147e4530784fb0a92b81d6ff4b0e610e.mp3","card_desc":"\u5728\u300a\u9001\u846c\u8fdb\u884c\u66f2\u300b\u4e2d\uff0c\u8096\u90a6\u5199\u51fa\u4e86\u524d\u6240\u672a\u89c1\u7684\u4ee5\u53cc\u624b\u9f50\u594f\u76f8\u9694\u516b\u5ea6\u7684\u5355\u97f3\uff0c\u5f39\u51fa\u4e00\u6bb5\u8c03\u6027\u6a21\u7cca\u3001\u7ed3\u6784\u4e5f\u4e0d\u6e05\u695a\u7684\u97f3\u4e50\uff0c\u5374\u53c8\u4ee5\u8fd9\u4e2a\u5355\u97f3\u7ebf\u6761\u8868\u73b0\u201c\u5893\u5730\u91cc\u7684\u591c\u98ce\u201d\u3001\u201c\u575f\u5934\u4e0a\u7684\u9b3c\u706b\u201d\u3002","is_listened":"0","listen_percent":"0","listen_time":"0","is_finished":"0","is_vip_free":"1","background_img":"http:\/\/cdn.vistopia.com.cn\/1632992960393.png","author":"\u7126\u5143\u6ea5","is_vip_only":"0","share_free_count":"10","is_listen":"1"},{"article_id":"481444","content_id":"233","catalog_id":"1051","title":"06. \u6700\u7f8e\u7684\u97f3\u7b26\uff1a\u7a76\u7adf\u662f\u8c01\u53d1\u660e\u4e86\u591c\u66f2","sort_number":"07","status":"1","share_desc":"\u300a\u5982\u4f55\u542c\u61c2\u8096\u90a6\uff1a\u7126\u5143\u6ea5\u8096\u90a610\u8bb2\u300b","is_trial":"0","duration":"1547","duration_str":"25:47","media_type":"1","media_size":"24232","video_poster":"http:\/\/cdn.vistopia.com.cn\/upload_img.png","comment_count":"15","sample_media_key":"aud\/a8e97-\/b9fcb85d37dd798e6f14e386078a4132.mp3","vid":"v03265g10002ccdb72dj6f8ur9ie76vg","sample_vid":"v0d265g10002cce1nf1abc6lp42q57rg","card_data":"","media_key_full_url":"http:\/\/cdn.vistopia.com.cn\/d5fa8e97-3bc4-47bd-9f8a-f721f679f099.mp3","optional_media_key_full_url":"http:\/\/cdn5.vistopia.com.cn\/d5fa8e97-3bc4-47bd-9f8a-f721f679f099.mp3","share_url":"https:\/\/shop.vistopia.com.cn\/article?article_id=481444&share_uid=huLq5","media_type_en":"audio","content_media_type_en":"audio","type":"charge","content_url":"https:\/\/api.vistopia.com.cn\/api\/v1\/web\/article-content\/D9B2A","sample_media_full_url":"http:\/\/cdn.vistopia.com.cn\/aud\/a8e97-\/b9fcb85d37dd798e6f14e386078a4132.mp3","card_desc":"\u7b2c\u4e00\u4e2a\u5199\u4f5c\u94a2\u7434\u66f2\u5e76\u4ee5\u201cNocturne\u201d\uff0c\u201c\u591c\u66f2\u201d\u6765\u547d\u540d\u7684\u4eba\uff0c\u662f\u7231\u5c14\u5170\u94a2\u7434\u5bb6\u83f2\u5c14\u5fb7\uff0c\u4ed6\u4e8e1812\u5e74\u5728\u5723\u5f7c\u5f97\u5821\u6240\u51fa\u7248\u7684\u4e09\u9996\u591c\u66f2\uff0c\u662f\u94a2\u7434\u72ec\u594f\u591c\u66f2\u7684\u59cb\u7956\u3002","is_listened":"0","listen_percent":"0","listen_time":"0","is_finished":"0","is_vip_free":"1","background_img":"http:\/\/cdn.vistopia.com.cn\/1632992960393.png","author":"\u7126\u5143\u6ea5","is_vip_only":"0","share_free_count":"10","is_listen":"1"},{"article_id":"483294","content_id":"233","catalog_id":"1051","title":"07. \u53d9\u4e8b\u66f2\u9769\u547d\uff1a\u5982\u4f55\u7528\u97f3\u4e50\u8bf4\u6545\u4e8b","sort_number":"08","status":"1","share_desc":"\u300a\u5982\u4f55\u542c\u61c2\u8096\u90a6\uff1a\u7126\u5143\u6ea5\u8096\u90a610\u8bb2\u300b","is_trial":"0","duration":"1820","duration_str":"30:20","media_type":"1","media_size":"28504","video_poster":"http:\/\/cdn.vistopia.com.cn\/upload_img.png","comment_count":"19","sample_media_key":"aud\/950e9-\/150344bed6cd315adff82055167bb057.mp3","vid":"v03265g10002ccdb7haoktor4971j0l0","sample_vid":"v0d265g10002cce28t78v1n1s3nrvql0","card_data":"","media_key_full_url":"http:\/\/cdn.vistopia.com.cn\/fe5950e9-ab2d-4ea6-b222-43e6867e7165.mp3","optional_media_key_full_url":"http:\/\/cdn5.vistopia.com.cn\/fe5950e9-ab2d-4ea6-b222-43e6867e7165.mp3","share_url":"https:\/\/shop.vistopia.com.cn\/article?article_id=483294&share_uid=BNc51","media_type_en":"audio","content_media_type_en":"audio","type":"charge","content_url":"https:\/\/api.vistopia.com.cn\/api\/v1\/web\/article-content\/kPSGm","sample_media_full_url":"http:\/\/cdn.vistopia.com.cn\/aud\/950e9-\/150344bed6cd315adff82055167bb057.mp3","card_desc":"\u8096\u90a6\u6240\u505a\u7684\u201c\u5668\u4e50\u53d9\u4e8b\u66f2\u201d\u662f\u65e0\u8a00\u53d9\u4e8b\u66f2\uff0c\u4ed6\u4ee5\u4f5c\u54c1\u7d20\u6750\u548c\u7ed3\u6784\u6765\u8868\u73b0\u6545\u4e8b\uff0c\u628a\u594f\u9e23\u66f2\u5f0f\u3001\u8f6e\u65cb\u66f2\u3001\u53d8\u594f\u66f2\u7b49\u7b49\u6982\u5ff5\u540c\u6574\u4e3a\u4e00\uff0c\u521b\u9020\u51fa\u6240\u8c13\u7684\u201c\u65b0\u66f2\u7c7b\u53d9\u4e8b\u66f2\u201d\u3002","is_listened":"0","listen_percent":"0","listen_time":"0","is_finished":"0","is_vip_free":"1","background_img":"http:\/\/cdn.vistopia.com.cn\/1632992960393.png","author":"\u7126\u5143\u6ea5","is_vip_only":"0","share_free_count":"10","is_listen":"1"},{"article_id":"483344","content_id":"233","catalog_id":"1051","title":"08. \u4e0d\u80fd\u8fd9\u6837\u5f39\uff01\u8096\u90a6\u662f\u4e2a\u597d\u8001\u5e08\u5417","sort_number":"09","status":"1","share_desc":"\u300a\u5982\u4f55\u542c\u61c2\u8096\u90a6\uff1a\u7126\u5143\u6ea5\u8096\u90a610\u8bb2\u300b","is_trial":"0","duration":"2048","duration_str":"34:08","media_type":"1","media_size":"32055","video_poster":"http:\/\/cdn.vistopia.com.cn\/upload_img.png","comment_count":"16","sample_media_key":"aud\/497fe-\/4bef481fca9fe74b51be82f337d75f8b.mp3","vid":"v02265g10002ccdb7hkg3monqh2vvbqg","sample_vid":"v0d265g10002cce2999abc6lp42q5h70","card_data":"","media_key_full_url":"http:\/\/cdn.vistopia.com.cn\/95f497fe-ffc9-4308-a334-82f942b73a22.mp3","optional_media_key_full_url":"http:\/\/cdn5.vistopia.com.cn\/95f497fe-ffc9-4308-a334-82f942b73a22.mp3","share_url":"https:\/\/shop.vistopia.com.cn\/article?article_id=483344&share_uid=DIag9","media_type_en":"audio","content_media_type_en":"audio","type":"charge","content_url":"https:\/\/api.vistopia.com.cn\/api\/v1\/web\/article-content\/LZqiV","sample_media_full_url":"http:\/\/cdn.vistopia.com.cn\/aud\/497fe-\/4bef481fca9fe74b51be82f337d75f8b.mp3","card_desc":"\u8096\u90a6\u975e\u5e38\u8ba4\u771f\u5730\u770b\u5f85\u6559\u5b66\uff0c\u5bf9\u6f14\u594f\u53ef\u8bf4\u662f\u9531\u94e2\u5fc5\u8f83\uff0c\u5bf9\u5b66\u751f\u4e5f\u975e\u5e38\u6709\u8010\u5fc3\u3002\u6b63\u56e0\u5982\u6b64\uff0c\u6211\u4eec\u624d\u80fd\u591f\u4ece\u4ed6\u7684\u5b66\u751f\u7684\u56de\u5fc6\u4e2d\uff0c\u62fc\u51d1\u5efa\u7acb\u51fa\u4ed6\u7684\u6f14\u594f\u7cfb\u7edf\u8ddf\u97f3\u4e50\u7f8e\u5b66\u3002","is_listened":"0","listen_percent":"0","listen_time":"0","is_finished":"0","is_vip_free":"1","background_img":"http:\/\/cdn.vistopia.com.cn\/1632992960393.png","author":"\u7126\u5143\u6ea5","is_vip_only":"0","share_free_count":"10","is_listen":"1"},{"article_id":"485894","content_id":"233","catalog_id":"1051","title":"09. \u8ba9\u7231\u5316\u4f5c\u8bb0\u5fc6\uff0c\u75db\u82e6\u878d\u6210\u6b4c\uff1a\u8096\u90a6\u665a\u671f\u53f2\u8bd7","sort_number":"10","status":"1","share_desc":"\u300a\u5982\u4f55\u542c\u61c2\u8096\u90a6\uff1a\u7126\u5143\u6ea5\u8096\u90a610\u8bb2\u300b","is_trial":"0","duration":"2304","duration_str":"38:24","media_type":"1","media_size":"36060","video_poster":"http:\/\/cdn.vistopia.com.cn\/upload_img.png","comment_count":"18","sample_media_key":"aud\/9906b-\/7831427f98c8c43b3a7e46f138a00443.mp3","vid":"v03265g10002ccdb802oktor4971j0pg","sample_vid":"v0d265g10002cce2vphabc6lp42q61hg","card_data":"","media_key_full_url":"http:\/\/cdn.vistopia.com.cn\/1919906b-bb49-44a3-a7b8-036a388e0177.mp3","optional_media_key_full_url":"http:\/\/cdn5.vistopia.com.cn\/1919906b-bb49-44a3-a7b8-036a388e0177.mp3","share_url":"https:\/\/shop.vistopia.com.cn\/article?article_id=485894&share_uid=tYAmo","media_type_en":"audio","content_media_type_en":"audio","type":"charge","content_url":"https:\/\/api.vistopia.com.cn\/api\/v1\/web\/article-content\/UH7TX","sample_media_full_url":"http:\/\/cdn.vistopia.com.cn\/aud\/9906b-\/7831427f98c8c43b3a7e46f138a00443.mp3","card_desc":"30\u5c81\u4ee5\u540e\u7684\u8096\u90a6\uff0c\u5199\u4f5c\u548c\u51fa\u7248\u7684\u4f5c\u54c1\u8d8a\u6765\u8d8a\u5c11\uff0c\u8fd9\u662f\u5426\u8868\u793a\u8096\u90a6\u7684\u8eab\u4f53\u8870\u9000\u6216\u7075\u611f\u67af\u7aed\u5462\uff1f\u5176\u5b9e\u771f\u6b63\u5bfc\u81f4\u4ed6\u521b\u4f5c\u51cf\u5c11\u7684\u56e0\u7d20\uff0c\u662f\u4ed6\u6240\u9762\u4e34\u7684\u4e2a\u4eba\u521b\u4f5c\u5371\u673a\u3002","is_listened":"0","listen_percent":"0","listen_time":"0","is_finished":"0","is_vip_free":"1","background_img":"http:\/\/cdn.vistopia.com.cn\/1632992960393.png","author":"\u7126\u5143\u6ea5","is_vip_only":"0","share_free_count":"10","is_listen":"1"},{"article_id":"486544","content_id":"233","catalog_id":"1051","title":"10. \u8fdb\u9636\uff1a\u8096\u90a6\u5982\u4f55\u6539\u53d8\u4e86\u94a2\u7434\u548c\u6211\u4eec\u7684\u8033\u6735","sort_number":"11","status":"1","share_desc":"\u300a\u5982\u4f55\u542c\u61c2\u8096\u90a6\uff1a\u7126\u5143\u6ea5\u8096\u90a610\u8bb2\u300b","is_trial":"0","duration":"1544","duration_str":"25:44","media_type":"1","media_size":"24188","video_poster":"http:\/\/cdn.vistopia.com.cn\/upload_img.png","comment_count":"20","sample_media_key":"aud\/a52b4-\/0cdd86daf8e2742a560dbea369d26ce7.mp3","vid":"v03265g10002ccdb80ioktor4971j0qg","sample_vid":"v0d265g10002cce35d78v1n1s3ns0e5g","card_data":"","media_key_full_url":"http:\/\/cdn.vistopia.com.cn\/389a52b4-d0c1-485b-81dc-a17f285eebd1.mp3","optional_media_key_full_url":"http:\/\/cdn5.vistopia.com.cn\/389a52b4-d0c1-485b-81dc-a17f285eebd1.mp3","share_url":"https:\/\/shop.vistopia.com.cn\/article?article_id=486544&share_uid=7OZNq","media_type_en":"audio","content_media_type_en":"audio","type":"charge","content_url":"https:\/\/api.vistopia.com.cn\/api\/v1\/web\/article-content\/1I4DJ","sample_media_full_url":"http:\/\/cdn.vistopia.com.cn\/aud\/a52b4-\/0cdd86daf8e2742a560dbea369d26ce7.mp3","card_desc":"\u8096\u90a6\u600e\u6837\u5f71\u54cd\u4e86\u4ed6\u7684\u65f6\u4ee3\uff0c\u53c8\u5982\u4f55\u5f71\u54cd\u4e86\u6211\u4eec\uff1f","is_listened":"0","listen_percent":"0","listen_time":"0","is_finished":"0","is_vip_free":"1","background_img":"http:\/\/cdn.vistopia.com.cn\/1632992960393.png","author":"\u7126\u5143\u6ea5","is_vip_only":"0","share_free_count":"10","is_listen":"1"},{"article_id":"490944","content_id":"233","catalog_id":"1051","title":"\u9648\u8428 \u00d7 \u7126\u5143\u6ea5\uff1a\u7406\u6027\u4e0e\u611f\u6027\u7684\u7ed3\u5408 | \u7279\u522b\u4f01\u5212","sort_number":"12","status":"1","share_desc":"\u300a\u5982\u4f55\u542c\u61c2\u8096\u90a6\uff1a\u7126\u5143\u6ea5\u8096\u90a610\u8bb2\u300b","is_trial":"1","duration":"3834","duration_str":"01:03:54","media_type":"1","media_size":"59104","video_poster":"http:\/\/cdn.vistopia.com.cn\/upload_img.png","comment_count":"31","sample_media_key":"aud\/ab2e1-\/21cd75a8e41cd45774e9cd10df649855.mp3","vid":"v02265g10002ccdb8v2r686qbamp782g","sample_vid":"v0d265g10002cce4el9abc6lp42q6t9g","card_data":"","media_key_full_url":"http:\/\/cdn.vistopia.com.cn\/491ab2e1-b6db-4172-b95b-6557a227a8c0.mp3","optional_media_key_full_url":"http:\/\/cdn5.vistopia.com.cn\/491ab2e1-b6db-4172-b95b-6557a227a8c0.mp3","share_url":"https:\/\/shop.vistopia.com.cn\/article?article_id=490944","media_type_en":"audio","content_media_type_en":"audio","type":"charge","content_url":"https:\/\/api.vistopia.com.cn\/api\/v1\/web\/article-content\/n_RrE","sample_media_full_url":"http:\/\/cdn.vistopia.com.cn\/aud\/ab2e1-\/21cd75a8e41cd45774e9cd10df649855.mp3","card_desc":"\u7406\u6027\u548c\u611f\u6027\u7ed3\u5408\u8bde\u751f\u7684\u4f5c\u54c1\uff0c\u66f4\u52a0\u7ecf\u5f97\u8d77\u63a8\u6572\u3002","is_listened":"0","listen_percent":"0","listen_time":"0","is_finished":"0","is_vip_free":"1","background_img":"http:\/\/cdn.vistopia.com.cn\/1632992960393.png","author":"\u7126\u5143\u6ea5","is_vip_only":"0","share_free_count":"0","is_listen":"1"}]}}