{"status":"success","data":{"id":"277","title":"\u4e0e\u8bd7\u76f8\u9047\uff1a\u5317\u5c9b\u4f5c\u54c1\u6717\u8bfb\u4f1a","small_background_img":"http:\/\/cdn.vistopia.com.cn\/1650944047683.jpg","background_img":"http:\/\/cdn.vistopia.com.cn\/1650944043243.jpg","catalog_type":"2","type":"charge","complete_class_price":"0.00","promotion_price":"0.00","promotion_desc":"","is_promotion":"0","media_type":"2","is_vip_free":"1","is_vip_only":"1","media_type_en":"video","author":"\u5317\u5c9b","is_subscribed":"0","is_purchased":"0","is_limited_free":"0","vip_type":"lixiangjia_trial","is_vip_expired":"0","old_vip_type":"","catalog":[{"catalog_id":"0","catalog_number":"01","catalog_title":"\u4e0e\u8bd7\u76f8\u9047\uff1a\u5317\u5c9b\u4f5c\u54c1\u6717\u8bfb\u4f1a","part":[{"article_id":"545394","content_id":"277","catalog_id":"0","title":"\u4e0e\u8bd7\u76f8\u9047\uff1a\u5317\u5c9b\u4f5c\u54c1\u6717\u8bfb\u4f1a\uff08\u4e0a\uff09","sort_number":"01","status":"1","share_desc":"\u8bd7\u610f\u7684\u65e5\u5b50\u5f00\u59cb\u4e86\u3002","is_trial":"0","duration":"4030","duration_str":"01:07:10","media_type":"2","media_size":"876808","video_poster":"http:\/\/cdn.vistopia.com.cn\/1650943084975.png","sample_media_key":null,"comment_count":"14","vid":"v02265g10002cccsfcir686qbamp260g","sample_vid":"","media_key_full_url":null,"optional_media_key_full_url":null,"share_url":"https:\/\/shop.vistopia.com.cn\/article?article_id=545394","media_type_en":"video","content_media_type_en":"video","type":"charge","content_url":"https:\/\/api.vistopia.com.cn\/api\/v1\/web\/article-content\/wVrDV","media_files":[{"media_id":"3109","media_con_id":"277","media_type":"2","media_size":"859282","media_key":"vod\/a32d36\/691fa92c7323e88954c7f2fef7f03231_1920x1080.m3u8","quality":"1080","is_sample":"0","media_key_full_url":"http:\/\/cdn.vistopia.com.cn\/vod\/a32d36\/691fa92c7323e88954c7f2fef7f03231_1920x1080.m3u8","optional_media_key_full_url":"http:\/\/cdn5.vistopia.com.cn\/vod\/a32d36\/691fa92c7323e88954c7f2fef7f03231_1920x1080.m3u8","media_type_en":"video","quality_name":"\u84dd\u51491080P","short_quality_name":"\u84dd\u5149","is_default":"0","media_size_en":"839MB"},{"media_id":"3110","media_con_id":"277","media_type":"2","media_size":"858742","media_key":"vod\/a32d36\/691fa92c7323e88954c7f2fef7f03231_1280x720.m3u8","quality":"720","is_sample":"0","media_key_full_url":"http:\/\/cdn.vistopia.com.cn\/vod\/a32d36\/691fa92c7323e88954c7f2fef7f03231_1280x720.m3u8","optional_media_key_full_url":"http:\/\/cdn5.vistopia.com.cn\/vod\/a32d36\/691fa92c7323e88954c7f2fef7f03231_1280x720.m3u8","media_type_en":"video","quality_name":"\u8d85\u6e05720P","short_quality_name":"\u8d85\u6e05","is_default":"1","media_size_en":"839MB"},{"media_id":"3111","media_con_id":"277","media_type":"2","media_size":"562921","media_key":"vod\/a32d36\/691fa92c7323e88954c7f2fef7f03231_854x480.m3u8","quality":"480","is_sample":"0","media_key_full_url":"http:\/\/cdn.vistopia.com.cn\/vod\/a32d36\/691fa92c7323e88954c7f2fef7f03231_854x480.m3u8","optional_media_key_full_url":"http:\/\/cdn5.vistopia.com.cn\/vod\/a32d36\/691fa92c7323e88954c7f2fef7f03231_854x480.m3u8","media_type_en":"video","quality_name":"\u9ad8\u6e05480P","short_quality_name":"\u9ad8\u6e05","is_default":"0","media_size_en":"550MB"}],"sample_media_full_url":"","is_listened":"0","listen_percent":"0","listen_time":"0","is_finished":"0"},{"article_id":"545444","content_id":"277","catalog_id":"0","title":"\u4e0e\u8bd7\u76f8\u9047\uff1a\u5317\u5c9b\u4f5c\u54c1\u6717\u8bfb\u4f1a\uff08\u4e0b\uff09","sort_number":"02","status":"1","share_desc":"\u662f\u7231\u7684\u5149\u7ebf\u9192\u6765\uff0c\u7167\u4eae\u96f6\u5ea6\u4ee5\u4e0a\u7684\u98ce\u666f\u3002","is_trial":"0","duration":"3632","duration_str":"01:00:32","media_type":"2","media_size":"799837","video_poster":"http:\/\/cdn.vistopia.com.cn\/1650943508001.png","sample_media_key":null,"comment_count":"7","vid":"v03265g10002cccsfiih3be9vs2845t0","sample_vid":"","media_key_full_url":null,"optional_media_key_full_url":null,"share_url":"https:\/\/shop.vistopia.com.cn\/article?article_id=545444","media_type_en":"video","content_media_type_en":"video","type":"charge","content_url":"https:\/\/api.vistopia.com.cn\/api\/v1\/web\/article-content\/1lxcn","media_files":[{"media_id":"3115","media_con_id":"277","media_type":"2","media_size":"788552","media_key":"vod\/396ede\/4424df3f88ff498760c3d62616d23335_1920x1080.m3u8","quality":"1080","is_sample":"0","media_key_full_url":"http:\/\/cdn.vistopia.com.cn\/vod\/396ede\/4424df3f88ff498760c3d62616d23335_1920x1080.m3u8","optional_media_key_full_url":"http:\/\/cdn5.vistopia.com.cn\/vod\/396ede\/4424df3f88ff498760c3d62616d23335_1920x1080.m3u8","media_type_en":"video","quality_name":"\u84dd\u51491080P","short_quality_name":"\u84dd\u5149","is_default":"0","media_size_en":"770MB"},{"media_id":"3116","media_con_id":"277","media_type":"2","media_size":"787142","media_key":"vod\/396ede\/4424df3f88ff498760c3d62616d23335_1280x720.m3u8","quality":"720","is_sample":"0","media_key_full_url":"http:\/\/cdn.vistopia.com.cn\/vod\/396ede\/4424df3f88ff498760c3d62616d23335_1280x720.m3u8","optional_media_key_full_url":"http:\/\/cdn5.vistopia.com.cn\/vod\/396ede\/4424df3f88ff498760c3d62616d23335_1280x720.m3u8","media_type_en":"video","quality_name":"\u8d85\u6e05720P","short_quality_name":"\u8d85\u6e05","is_default":"1","media_size_en":"769MB"},{"media_id":"3117","media_con_id":"277","media_type":"2","media_size":"509906","media_key":"vod\/396ede\/4424df3f88ff498760c3d62616d23335_854x480.m3u8","quality":"480","is_sample":"0","media_key_full_url":"http:\/\/cdn.vistopia.com.cn\/vod\/396ede\/4424df3f88ff498760c3d62616d23335_854x480.m3u8","optional_media_key_full_url":"http:\/\/cdn5.vistopia.com.cn\/vod\/396ede\/4424df3f88ff498760c3d62616d23335_854x480.m3u8","media_type_en":"video","quality_name":"\u9ad8\u6e05480P","short_quality_name":"\u9ad8\u6e05","is_default":"0","media_size_en":"498MB"}],"sample_media_full_url":"","is_listened":"0","listen_percent":"0","listen_time":"0","is_finished":"0"}]}]}}